cheminformatics/__init__.py
cheminformatics/utils.py
cheminformatics/edu/__init__.py
cheminformatics/edu/eln.py
gressling-0.0.6.dist-info/METADATA
gressling-0.0.6.dist-info/WHEEL
gressling-0.0.6.dist-info/top_level.txt
gressling-0.0.6.dist-info/RECORD
