Metadata-Version: 2.1
Name: gressling
Version: 0.0.6
Summary: Cheminformatics toolset for lectures at Humboldt University Berlin
Author: Gressling, T.
Author-email: thorsten.gressling@gressling.com
